mineplayer/__init__.py
mineplayer/mineplayer.py
mineplayer/useravatar.py
mineplayer/errors/__init__.py
mineplayer/errors/customerror.py
mineplayer/info/__init__.py
mineplayer/info/info.py
MinePlayer-1.0.4.dist-info/LICENSE
MinePlayer-1.0.4.dist-info/METADATA
MinePlayer-1.0.4.dist-info/WHEEL
MinePlayer-1.0.4.dist-info/top_level.txt
MinePlayer-1.0.4.dist-info/RECORD
