Metadata-Version: 2.1
Name: MinePlayer
Version: 1.0.4
Summary: A module to parse Minecraft player information
Home-page: https://github.com/510208/minePlayer
Download-URL: https://pypi.org/project/mineplayer/
Author: SamHacker
Author-email: xux510208@gmail.com
License: GNU General Public License v3.0
Project-URL: Source, https://github.com/510208/minePlayer
Project-URL: Documentation, https://github.com/510208/minePlayer/wiki
Classifier: Programming Language :: Python :: 3.7
Classifier: Programming Language :: Python :: 3.8
Classifier: Programming Language :: Python :: 3.9
Classifier: Programming Language :: Python :: 3.10
Classifier: Programming Language :: Python :: 3.11
Requires-Python: >=3.7
License-File: LICENSE
Requires-Dist: requests
Provides-Extra: dev
